axm/__init__.py
axm/core/__init__.py
axm/core/agent.py
axm/core/decorators.py
axm/core/multi_agent.py
axm/core/planning_agent.py
axm/core/types.py
axm/llm/__init__.py
axm/llm/anthropic.py
axm/llm/base.py
axm/llm/openai.py
axm/mcp/__init__.py
axm/mcp/server.py
axm/memory/__init__.py
axm/memory/conversation.py
axm/tools/__init__.py
axm/tools/base.py
axm/utils/__init__.py
axm_agent-0.1.2.dist-info/licenses/LICENSE
axm_agent-0.1.2.dist-info/METADATA
axm_agent-0.1.2.dist-info/WHEEL
axm_agent-0.1.2.dist-info/top_level.txt
axm_agent-0.1.2.dist-info/RECORD
